voucherify_core_mcp/__init__.py
voucherify_core_mcp/_version.py
voucherify_core_mcp/client.py
voucherify_core_mcp/main.py
voucherify_core_mcp/pagination.py
voucherify_core_mcp/py.typed
voucherify_core_mcp/server.py
voucherify_core_mcp-1.1.0.dist-info/METADATA
voucherify_core_mcp-1.1.0.dist-info/WHEEL
voucherify_core_mcp-1.1.0.dist-info/entry_points.txt
voucherify_core_mcp-1.1.0.dist-info/licenses/LICENSE
voucherify_core_mcp-1.1.0.dist-info/RECORD
