Metadata-Version: 2.4
Name: voucherify-core-mcp
Version: 1.1.0
Summary: A Model Context Protocol (MCP) server for integrating with Voucherify services
Project-URL: Homepage, https://github.com/voucherifyio/core-mcp
Project-URL: Documentation, https://github.com/voucherifyio/core-mcp#readme
Project-URL: Repository, https://github.com/voucherifyio/core-mcp.git
Project-URL: Issues, https://github.com/voucherifyio/core-mcp/issues
Project-URL: Changelog, https://github.com/voucherifyio/core-mcp/blob/main/CHANGELOG.md
Author-email: Voucherify Dev Team <support@voucherify.io>
Maintainer-email: Voucherify Dev Team <support@voucherify.io>
License: MIT
License-File: LICENSE
Keywords: coupons,mcp,model-context-protocol,promotions,voucherify,vouchers
Classifier: Development Status :: 4 - Beta
Classifier: Intended Audience :: Developers
Classifier: License :: OSI Approved :: MIT License
Classifier: Operating System :: OS Independent
Classifier: Programming Language :: Python :: 3
Classifier: Programming Language :: Python :: 3.12
Classifier: Programming Language :: Python :: 3.13
Classifier: Topic :: Internet :: WWW/HTTP :: HTTP Servers
Classifier: Topic :: Office/Business :: Financial :: Point-Of-Sale
Classifier: Topic :: Software Development :: Libraries :: Python Modules
Requires-Python: >=3.12
Requires-Dist: fastmcp>=2.12.0
Requires-Dist: httpx>=0.28.1
Requires-Dist: python-dotenv>=1.1.1
Requires-Dist: requests>=2.32.4
Provides-Extra: dev
Requires-Dist: litellm>=1.74.3; extra == 'dev'
Requires-Dist: mcp[cli]>=1.11.0; extra == 'dev'
Requires-Dist: pytest-asyncio>=0.23.8; extra == 'dev'
Requires-Dist: pytest>=8.3.0; extra == 'dev'
Requires-Dist: voucherify>=5.0.3; extra == 'dev'
Provides-Extra: test
Requires-Dist: pytest-asyncio>=0.23.8; extra == 'test'
Requires-Dist: pytest>=8.3.0; extra == 'test'
